brewt/bf_man.py
brewt/brew_class.py
brewt/brewt.py
brewt-1.2.0.dist-info/METADATA
brewt-1.2.0.dist-info/WHEEL
brewt-1.2.0.dist-info/entry_points.txt
brewt-1.2.0.dist-info/top_level.txt
brewt-1.2.0.dist-info/RECORD
